hw_2/__init__.py
hw_2/task_2_1_main.py
hw_2/task_2_2_main.py
hw_2/tex_generator.py
latex_table_and_image_generator-0.3.0.dist-info/METADATA
latex_table_and_image_generator-0.3.0.dist-info/WHEEL
latex_table_and_image_generator-0.3.0.dist-info/top_level.txt
latex_table_and_image_generator-0.3.0.dist-info/RECORD
