Metadata-Version: 2.1
Name: latex-table-and-image-generator
Version: 0.3.0
Summary: A simple LaTeX table and image generator
Author: Aleksandr Shirshov
Author-email: sasshok21@gmail.com
